{
  "count": 55,
  "pairs": [
    {
      "symbol": "BTC/USDT:USDT",
      "base": "BTC",
      "quote": "USDT",
      "volume_24h_usd": 10681854831.48357,
      "last_price": 86910.4,
      "change_24h": -0.56,
      "type": "swap"
    },
    {
      "symbol": "ETH/USDT:USDT",
      "base": "ETH",
      "quote": "USDT",
      "volume_24h_usd": 7266882598.0264,
      "last_price": 2928.19,
      "change_24h": 0.02,
      "type": "swap"
    },
    {
      "symbol": "SOL/USDT:USDT",
      "base": "SOL",
      "quote": "USDT",
      "volume_24h_usd": 2528309727.0,
      "last_price": 121.43,
      "change_24h": -1.5,
      "type": "swap"
    },
    {
      "symbol": "XRP/USDT:USDT",
      "base": "XRP",
      "quote": "USDT",
      "volume_24h_usd": 952762196.3961,
      "last_price": 1.8446,
      "change_24h": -1.91,
      "type": "swap"
    },
    {
      "symbol": "DOGE/USDT:USDT",
      "base": "DOGE",
      "quote": "USDT",
      "volume_24h_usd": 634335195.07,
      "last_price": 0.12721,
      "change_24h": -1.7,
      "type": "swap"
    },
    {
      "symbol": "ZEC/USDT:USDT",
      "base": "ZEC",
      "quote": "USDT",
      "volume_24h_usd": 316311223.3975,
      "last_price": 406.92,
      "change_24h": -2.14,
      "type": "swap"
    },
    {
      "symbol": "LINK/USDT:USDT",
      "base": "LINK",
      "quote": "USDT",
      "volume_24h_usd": 246369353.6028,
      "last_price": 12.143,
      "change_24h": -1.08,
      "type": "swap"
    },
    {
      "symbol": "ADA/USDT:USDT",
      "base": "ADA",
      "quote": "USDT",
      "volume_24h_usd": 237772535.4093,
      "last_price": 0.3547,
      "change_24h": -1.66,
      "type": "swap"
    },
    {
      "symbol": "SUI/USDT:USDT",
      "base": "SUI",
      "quote": "USDT",
      "volume_24h_usd": 233353400.1733,
      "last_price": 1.399,
      "change_24h": -2.24,
      "type": "swap"
    },
    {
      "symbol": "AVAX/USDT:USDT",
      "base": "AVAX",
      "quote": "USDT",
      "volume_24h_usd": 213480753.4155,
      "last_price": 11.966,
      "change_24h": 0.21,
      "type": "swap"
    },
    {
      "symbol": "HYPE/USDT:USDT",
      "base": "HYPE",
      "quote": "USDT",
      "volume_24h_usd": 155958485.4015,
      "last_price": 23.827,
      "change_24h": -0.99,
      "type": "swap"
    },
    {
      "symbol": "BCH/USDT:USDT",
      "base": "BCH",
      "quote": "USDT",
      "volume_24h_usd": 137543881.6176,
      "last_price": 572.25,
      "change_24h": -0.74,
      "type": "swap"
    },
    {
      "symbol": "AAVE/USDT:USDT",
      "base": "AAVE",
      "quote": "USDT",
      "volume_24h_usd": 124624839.811,
      "last_price": 148.68,
      "change_24h": -1.02,
      "type": "swap"
    },
    {
      "symbol": "LTC/USDT:USDT",
      "base": "LTC",
      "quote": "USDT",
      "volume_24h_usd": 123993991.4169,
      "last_price": 75.74,
      "change_24h": -1.17,
      "type": "swap"
    },
    {
      "symbol": "TAO/USDT:USDT",
      "base": "TAO",
      "quote": "USDT",
      "volume_24h_usd": 123672229.694,
      "last_price": 207.7,
      "change_24h": -3.17,
      "type": "swap"
    },
    {
      "symbol": "ASTER/USDT:USDT",
      "base": "ASTER",
      "quote": "USDT",
      "volume_24h_usd": 120431605.332,
      "last_price": 0.6708,
      "change_24h": -1.68,
      "type": "swap"
    },
    {
      "symbol": "UNI/USDT:USDT",
      "base": "UNI",
      "quote": "USDT",
      "volume_24h_usd": 112180053.992,
      "last_price": 5.671,
      "change_24h": -1.04,
      "type": "swap"
    },
    {
      "symbol": "PIPPIN/USDT:USDT",
      "base": "PIPPIN",
      "quote": "USDT",
      "volume_24h_usd": 102773597.3608,
      "last_price": 0.49352,
      "change_24h": 13.81,
      "type": "swap"
    },
    {
      "symbol": "PEPE/USDT:USDT",
      "base": "PEPE",
      "quote": "USDT",
      "volume_24h_usd": 98288887.61,
      "last_price": 3.852e-06,
      "change_24h": -1.78,
      "type": "swap"
    },
    {
      "symbol": "NEAR/USDT:USDT",
      "base": "NEAR",
      "quote": "USDT",
      "volume_24h_usd": 82429949.166,
      "last_price": 1.45,
      "change_24h": -2.42,
      "type": "swap"
    },
    {
      "symbol": "BNB/USDT:USDT",
      "base": "BNB",
      "quote": "USDT",
      "volume_24h_usd": 79081947.21,
      "last_price": 838.2,
      "change_24h": -0.72,
      "type": "swap"
    },
    {
      "symbol": "DOT/USDT:USDT",
      "base": "DOT",
      "quote": "USDT",
      "volume_24h_usd": 72593397.1368,
      "last_price": 1.724,
      "change_24h": -1.26,
      "type": "swap"
    },
    {
      "symbol": "XLM/USDT:USDT",
      "base": "XLM",
      "quote": "USDT",
      "volume_24h_usd": 57989206.1272,
      "last_price": 0.21363,
      "change_24h": -1.36,
      "type": "swap"
    },
    {
      "symbol": "SHIB/USDT:USDT",
      "base": "SHIB",
      "quote": "USDT",
      "volume_24h_usd": 53449051.239535,
      "last_price": 7.001e-06,
      "change_24h": -1.32,
      "type": "swap"
    },
    {
      "symbol": "NIGHT/USDT:USDT",
      "base": "NIGHT",
      "quote": "USDT",
      "volume_24h_usd": 49864386.765,
      "last_price": 0.07593,
      "change_24h": -5.22,
      "type": "swap"
    },
    {
      "symbol": "TONCOIN/USDT:USDT",
      "base": "TONCOIN",
      "quote": "USDT",
      "volume_24h_usd": 47944046.24,
      "last_price": 1.461,
      "change_24h": 0.06,
      "type": "swap"
    },
    {
      "symbol": "BEAT/USDT:USDT",
      "base": "BEAT",
      "quote": "USDT",
      "volume_24h_usd": 45780101.9649,
      "last_price": 2.3,
      "change_24h": -12.58,
      "type": "swap"
    },
    {
      "symbol": "HBAR/USDT:USDT",
      "base": "HBAR",
      "quote": "USDT",
      "volume_24h_usd": 43591628.87777,
      "last_price": 0.10897,
      "change_24h": -0.89,
      "type": "swap"
    },
    {
      "symbol": "H/USDT:USDT",
      "base": "H",
      "quote": "USDT",
      "volume_24h_usd": 39773400.02927,
      "last_price": 0.16399,
      "change_24h": -7.6,
      "type": "swap"
    },
    {
      "symbol": "XAUT/USDT:USDT",
      "base": "XAUT",
      "quote": "USDT",
      "volume_24h_usd": 38807149.9957,
      "last_price": 4494.4,
      "change_24h": 0.73,
      "type": "swap"
    },
    {
      "symbol": "FARTCOIN/USDT:USDT",
      "base": "FARTCOIN",
      "quote": "USDT",
      "volume_24h_usd": 38343333.328,
      "last_price": 0.2801,
      "change_24h": 2.0,
      "type": "swap"
    },
    {
      "symbol": "ENA/USDT:USDT",
      "base": "ENA",
      "quote": "USDT",
      "volume_24h_usd": 38268053.968,
      "last_price": 0.1962,
      "change_24h": -0.35,
      "type": "swap"
    },
    {
      "symbol": "TRUMPOFFICIAL/USDT:USDT",
      "base": "TRUMPOFFICIAL",
      "quote": "USDT",
      "volume_24h_usd": 33736189.7609,
      "last_price": 4.904,
      "change_24h": -0.1,
      "type": "swap"
    },
    {
      "symbol": "ETC/USDT:USDT",
      "base": "ETC",
      "quote": "USDT",
      "volume_24h_usd": 31006942.6121,
      "last_price": 11.861,
      "change_24h": -1.41,
      "type": "swap"
    },
    {
      "symbol": "WLD/USDT:USDT",
      "base": "WLD",
      "quote": "USDT",
      "volume_24h_usd": 25295427.9338,
      "last_price": 0.4814,
      "change_24h": -1.51,
      "type": "swap"
    },
    {
      "symbol": "ICP/USDT:USDT",
      "base": "ICP",
      "quote": "USDT",
      "volume_24h_usd": 24114834.62807,
      "last_price": 2.976,
      "change_24h": 0.84,
      "type": "swap"
    },
    {
      "symbol": "WIF/USDT:USDT",
      "base": "WIF",
      "quote": "USDT",
      "volume_24h_usd": 22991760.942,
      "last_price": 0.3134,
      "change_24h": -1.47,
      "type": "swap"
    },
    {
      "symbol": "RAVE/USDT:USDT",
      "base": "RAVE",
      "quote": "USDT",
      "volume_24h_usd": 22857274.297,
      "last_price": 0.5547,
      "change_24h": -3.56,
      "type": "swap"
    },
    {
      "symbol": "WLFI/USDT:USDT",
      "base": "WLFI",
      "quote": "USDT",
      "volume_24h_usd": 19976597.647,
      "last_price": 0.1304,
      "change_24h": -0.76,
      "type": "swap"
    },
    {
      "symbol": "PUMPFUN/USDT:USDT",
      "base": "PUMPFUN",
      "quote": "USDT",
      "volume_24h_usd": 17435372.0129,
      "last_price": 0.001692,
      "change_24h": -2.75,
      "type": "swap"
    },
    {
      "symbol": "CHZ/USDT:USDT",
      "base": "CHZ",
      "quote": "USDT",
      "volume_24h_usd": 16154028.82346,
      "last_price": 0.035,
      "change_24h": 0.98,
      "type": "swap"
    },
    {
      "symbol": "APT/USDT:USDT",
      "base": "APT",
      "quote": "USDT",
      "volume_24h_usd": 15216797.66806,
      "last_price": 1.5727,
      "change_24h": -0.51,
      "type": "swap"
    },
    {
      "symbol": "JELLYJELLY/USDT:USDT",
      "base": "JELLYJELLY",
      "quote": "USDT",
      "volume_24h_usd": 14816772.6461,
      "last_price": 0.077,
      "change_24h": 1.66,
      "type": "swap"
    },
    {
      "symbol": "FOLKS/USDT:USDT",
      "base": "FOLKS",
      "quote": "USDT",
      "volume_24h_usd": 14366368.855,
      "last_price": 4.4,
      "change_24h": -11.54,
      "type": "swap"
    },
    {
      "symbol": "PENGU/USDT:USDT",
      "base": "PENGU",
      "quote": "USDT",
      "volume_24h_usd": 14028592.52585,
      "last_price": 0.008579,
      "change_24h": -2.12,
      "type": "swap"
    },
    {
      "symbol": "ARB/USDT:USDT",
      "base": "ARB",
      "quote": "USDT",
      "volume_24h_usd": 13523614.7607,
      "last_price": 0.1848,
      "change_24h": 0.81,
      "type": "swap"
    },
    {
      "symbol": "XMR/USDT:USDT",
      "base": "XMR",
      "quote": "USDT",
      "volume_24h_usd": 13492020.4156,
      "last_price": 429.23,
      "change_24h": -4.05,
      "type": "swap"
    },
    {
      "symbol": "INJ/USDT:USDT",
      "base": "INJ",
      "quote": "USDT",
      "volume_24h_usd": 13327926.072,
      "last_price": 4.481,
      "change_24h": -1.45,
      "type": "swap"
    },
    {
      "symbol": "KAS/USDT:USDT",
      "base": "KAS",
      "quote": "USDT",
      "volume_24h_usd": 12939712.49,
      "last_price": 0.04433,
      "change_24h": -0.67,
      "type": "swap"
    },
    {
      "symbol": "TIA/USDT:USDT",
      "base": "TIA",
      "quote": "USDT",
      "volume_24h_usd": 11867452.1403,
      "last_price": 0.4342,
      "change_24h": -1.92,
      "type": "swap"
    },
    {
      "symbol": "D/USDT:USDT",
      "base": "D",
      "quote": "USDT",
      "volume_24h_usd": 11452343.9343,
      "last_price": 0.01567,
      "change_24h": 18.89,
      "type": "swap"
    },
    {
      "symbol": "ONDO/USDT:USDT",
      "base": "ONDO",
      "quote": "USDT",
      "volume_24h_usd": 10876545.189,
      "last_price": 0.3767,
      "change_24h": -2.25,
      "type": "swap"
    },
    {
      "symbol": "ICNT/USDT:USDT",
      "base": "ICNT",
      "quote": "USDT",
      "volume_24h_usd": 10855349.0293,
      "last_price": 0.5037,
      "change_24h": -4.87,
      "type": "swap"
    },
    {
      "symbol": "OP/USDT:USDT",
      "base": "OP",
      "quote": "USDT",
      "volume_24h_usd": 10445781.0097,
      "last_price": 0.265,
      "change_24h": -0.11,
      "type": "swap"
    },
    {
      "symbol": "ETHFI/USDT:USDT",
      "base": "ETHFI",
      "quote": "USDT",
      "volume_24h_usd": 10002163.6141,
      "last_price": 0.6777,
      "change_24h": -3.21,
      "type": "swap"
    }
  ],
  "symbols": [
    "BTC/USDT:USDT",
    "ETH/USDT:USDT",
    "SOL/USDT:USDT",
    "XRP/USDT:USDT",
    "DOGE/USDT:USDT",
    "ZEC/USDT:USDT",
    "LINK/USDT:USDT",
    "ADA/USDT:USDT",
    "SUI/USDT:USDT",
    "AVAX/USDT:USDT",
    "HYPE/USDT:USDT",
    "BCH/USDT:USDT",
    "AAVE/USDT:USDT",
    "LTC/USDT:USDT",
    "TAO/USDT:USDT",
    "ASTER/USDT:USDT",
    "UNI/USDT:USDT",
    "PIPPIN/USDT:USDT",
    "PEPE/USDT:USDT",
    "NEAR/USDT:USDT",
    "BNB/USDT:USDT",
    "DOT/USDT:USDT",
    "XLM/USDT:USDT",
    "SHIB/USDT:USDT",
    "NIGHT/USDT:USDT",
    "TONCOIN/USDT:USDT",
    "BEAT/USDT:USDT",
    "HBAR/USDT:USDT",
    "H/USDT:USDT",
    "XAUT/USDT:USDT",
    "FARTCOIN/USDT:USDT",
    "ENA/USDT:USDT",
    "TRUMPOFFICIAL/USDT:USDT",
    "ETC/USDT:USDT",
    "WLD/USDT:USDT",
    "ICP/USDT:USDT",
    "WIF/USDT:USDT",
    "RAVE/USDT:USDT",
    "WLFI/USDT:USDT",
    "PUMPFUN/USDT:USDT",
    "CHZ/USDT:USDT",
    "APT/USDT:USDT",
    "JELLYJELLY/USDT:USDT",
    "FOLKS/USDT:USDT",
    "PENGU/USDT:USDT",
    "ARB/USDT:USDT",
    "XMR/USDT:USDT",
    "INJ/USDT:USDT",
    "KAS/USDT:USDT",
    "TIA/USDT:USDT",
    "D/USDT:USDT",
    "ONDO/USDT:USDT",
    "ICNT/USDT:USDT",
    "OP/USDT:USDT",
    "ETHFI/USDT:USDT"
  ]
}